mathInterval/__init__.py
mathInterval/_mathInterval.cpython-310-aarch64-linux-gnu.so
mathInterval/_mathInterval/__init__.pyi
mathInterval/_mathInterval/policy.pyi
mathinterval-0.5.0.dist-info/METADATA
mathinterval-0.5.0.dist-info/WHEEL
mathinterval-0.5.0.dist-info/RECORD
mathinterval-0.5.0.dist-info/licenses/LICENSE
