Metadata-Version: 2.2
Name: mathInterval
Version: 0.5.0
Summary: Fast C++ interval math bindings
Author-Email: Fedorrracora <valyanskiy.f2009@yandex.ru>
License: Apache-2.0
Requires-Python: >=3.8
